{"/*":["X-Frame-Options: DENY","X-XSS-Protection: 1; mode=block","X-Content-Type-Options: nosniff","Referrer-Policy: same-origin"],"/styles.58258c26a105758bd251.css":["Cache-Control: public, max-age=31536000, immutable"],"/commons-4eaa23a952bb2e3f0e80.js":["Cache-Control: public, max-age=31536000, immutable"],"/component---src-pages-chuppah-js-bb9e6662ed2c04672810.js":["Cache-Control: public, max-age=31536000, immutable"],"/component---src-pages-index-js-e827c8d8a24ea6b649f4.js":["Cache-Control: public, max-age=31536000, immutable"],"/2c796e83-51cd723d9298e9048f02.js":["Cache-Control: public, max-age=31536000, immutable"],"/de11a982ff915e8921f1ebc4496f3e7c96424b5d-7f3b73b81f840d28abaf.js":["Cache-Control: public, max-age=31536000, immutable"],"/component---src-pages-party-js-b420717cd09f9cdd9c40.js":["Cache-Control: public, max-age=31536000, immutable"],"/component---src-pages-rsvp-js-df7a103005b21350d38c.js":["Cache-Control: public, max-age=31536000, immutable"],"/a683a28d-a72d8d3440c87ca5b55b.js":["Cache-Control: public, max-age=31536000, immutable"],"/component---src-pages-share-js-55b61b1ad8da543fe935.js":["Cache-Control: public, max-age=31536000, immutable"],"/component---src-pages-photos-index-js-e85816f1054785553541.js":["Cache-Control: public, max-age=31536000, immutable"],"/component---src-pages-photos-past-js-e3e1c65ebe79e7af86f1.js":["Cache-Control: public, max-age=31536000, immutable"],"/component---src-pages-week-index-js-8a3ac4d461e28aa87edc.js":["Cache-Control: public, max-age=31536000, immutable"],"/component---src-pages-week-rsvp-js-6389775f2c66999926a7.js":["Cache-Control: public, max-age=31536000, immutable"],"/webpack-runtime-7c74ab8f8e4f51889197.js":["Cache-Control: public, max-age=31536000, immutable"],"/framework-094b0089736b8f621f0d.js":["Cache-Control: public, max-age=31536000, immutable"],"/app-b0e2cd7f5cc6fb4dd1ad.js":["Cache-Control: public, max-age=31536000, immutable"],"/static/*":["Cache-Control: public, max-age=31536000, immutable"],"/sw.js":["Cache-Control: public, max-age=0, must-revalidate"],"/chuppah/":["Link: </webpack-runtime-7c74ab8f8e4f51889197.js>; rel=preload; as=script; nopush","Link: </framework-094b0089736b8f621f0d.js>; rel=preload; as=script; nopush","Link: </app-b0e2cd7f5cc6fb4dd1ad.js>; rel=preload; as=script; nopush","Link: </commons-4eaa23a952bb2e3f0e80.js>; rel=preload; as=script; nopush","Link: </component---src-pages-chuppah-js-bb9e6662ed2c04672810.js>; rel=preload; as=script; nopush","Link: </page-data/app-data.json>; rel=preload; as=fetch; crossorigin; nopush","Link: </page-data/chuppah/page-data.json>; rel=preload; as=fetch; crossorigin; nopush"],"/":["Link: </webpack-runtime-7c74ab8f8e4f51889197.js>; rel=preload; as=script; nopush","Link: </framework-094b0089736b8f621f0d.js>; rel=preload; as=script; nopush","Link: </app-b0e2cd7f5cc6fb4dd1ad.js>; rel=preload; as=script; nopush","Link: </commons-4eaa23a952bb2e3f0e80.js>; rel=preload; as=script; nopush","Link: </component---src-pages-index-js-e827c8d8a24ea6b649f4.js>; rel=preload; as=script; nopush","Link: </page-data/app-data.json>; rel=preload; as=fetch; crossorigin; nopush","Link: </page-data/index/page-data.json>; rel=preload; as=fetch; crossorigin; nopush"],"/party/":["Link: </webpack-runtime-7c74ab8f8e4f51889197.js>; rel=preload; as=script; nopush","Link: </framework-094b0089736b8f621f0d.js>; rel=preload; as=script; nopush","Link: </app-b0e2cd7f5cc6fb4dd1ad.js>; rel=preload; as=script; nopush","Link: </2c796e83-51cd723d9298e9048f02.js>; rel=preload; as=script; nopush","Link: </commons-4eaa23a952bb2e3f0e80.js>; rel=preload; as=script; nopush","Link: </de11a982ff915e8921f1ebc4496f3e7c96424b5d-7f3b73b81f840d28abaf.js>; rel=preload; as=script; nopush","Link: </component---src-pages-party-js-b420717cd09f9cdd9c40.js>; rel=preload; as=script; nopush","Link: </page-data/app-data.json>; rel=preload; as=fetch; crossorigin; nopush","Link: </page-data/party/page-data.json>; rel=preload; as=fetch; crossorigin; nopush"],"/rsvp/":["Link: </webpack-runtime-7c74ab8f8e4f51889197.js>; rel=preload; as=script; nopush","Link: </framework-094b0089736b8f621f0d.js>; rel=preload; as=script; nopush","Link: </app-b0e2cd7f5cc6fb4dd1ad.js>; rel=preload; as=script; nopush","Link: </commons-4eaa23a952bb2e3f0e80.js>; rel=preload; as=script; nopush","Link: </component---src-pages-rsvp-js-df7a103005b21350d38c.js>; rel=preload; as=script; nopush","Link: </page-data/app-data.json>; rel=preload; as=fetch; crossorigin; nopush","Link: </page-data/rsvp/page-data.json>; rel=preload; as=fetch; crossorigin; nopush"],"/share/":["Link: </webpack-runtime-7c74ab8f8e4f51889197.js>; rel=preload; as=script; nopush","Link: </framework-094b0089736b8f621f0d.js>; rel=preload; as=script; nopush","Link: </app-b0e2cd7f5cc6fb4dd1ad.js>; rel=preload; as=script; nopush","Link: </a683a28d-a72d8d3440c87ca5b55b.js>; rel=preload; as=script; nopush","Link: </commons-4eaa23a952bb2e3f0e80.js>; rel=preload; as=script; nopush","Link: </de11a982ff915e8921f1ebc4496f3e7c96424b5d-7f3b73b81f840d28abaf.js>; rel=preload; as=script; nopush","Link: </component---src-pages-share-js-55b61b1ad8da543fe935.js>; rel=preload; as=script; nopush","Link: </page-data/app-data.json>; rel=preload; as=fetch; crossorigin; nopush","Link: </page-data/share/page-data.json>; rel=preload; as=fetch; crossorigin; nopush"],"/photos/":["Link: </webpack-runtime-7c74ab8f8e4f51889197.js>; rel=preload; as=script; nopush","Link: </framework-094b0089736b8f621f0d.js>; rel=preload; as=script; nopush","Link: </app-b0e2cd7f5cc6fb4dd1ad.js>; rel=preload; as=script; nopush","Link: </2c796e83-51cd723d9298e9048f02.js>; rel=preload; as=script; nopush","Link: </commons-4eaa23a952bb2e3f0e80.js>; rel=preload; as=script; nopush","Link: </de11a982ff915e8921f1ebc4496f3e7c96424b5d-7f3b73b81f840d28abaf.js>; rel=preload; as=script; nopush","Link: </component---src-pages-photos-index-js-e85816f1054785553541.js>; rel=preload; as=script; nopush","Link: </page-data/app-data.json>; rel=preload; as=fetch; crossorigin; nopush","Link: </page-data/photos/page-data.json>; rel=preload; as=fetch; crossorigin; nopush"],"/photos/past/":["Link: </webpack-runtime-7c74ab8f8e4f51889197.js>; rel=preload; as=script; nopush","Link: </framework-094b0089736b8f621f0d.js>; rel=preload; as=script; nopush","Link: </app-b0e2cd7f5cc6fb4dd1ad.js>; rel=preload; as=script; nopush","Link: </commons-4eaa23a952bb2e3f0e80.js>; rel=preload; as=script; nopush","Link: </component---src-pages-photos-past-js-e3e1c65ebe79e7af86f1.js>; rel=preload; as=script; nopush","Link: </page-data/app-data.json>; rel=preload; as=fetch; crossorigin; nopush","Link: </page-data/photos/past/page-data.json>; rel=preload; as=fetch; crossorigin; nopush"],"/week/":["Link: </webpack-runtime-7c74ab8f8e4f51889197.js>; rel=preload; as=script; nopush","Link: </framework-094b0089736b8f621f0d.js>; rel=preload; as=script; nopush","Link: </app-b0e2cd7f5cc6fb4dd1ad.js>; rel=preload; as=script; nopush","Link: </2c796e83-51cd723d9298e9048f02.js>; rel=preload; as=script; nopush","Link: </commons-4eaa23a952bb2e3f0e80.js>; rel=preload; as=script; nopush","Link: </de11a982ff915e8921f1ebc4496f3e7c96424b5d-7f3b73b81f840d28abaf.js>; rel=preload; as=script; nopush","Link: </component---src-pages-week-index-js-8a3ac4d461e28aa87edc.js>; rel=preload; as=script; nopush","Link: </page-data/app-data.json>; rel=preload; as=fetch; crossorigin; nopush","Link: </page-data/week/page-data.json>; rel=preload; as=fetch; crossorigin; nopush"],"/week/rsvp/":["Link: </webpack-runtime-7c74ab8f8e4f51889197.js>; rel=preload; as=script; nopush","Link: </framework-094b0089736b8f621f0d.js>; rel=preload; as=script; nopush","Link: </app-b0e2cd7f5cc6fb4dd1ad.js>; rel=preload; as=script; nopush","Link: </commons-4eaa23a952bb2e3f0e80.js>; rel=preload; as=script; nopush","Link: </component---src-pages-week-rsvp-js-6389775f2c66999926a7.js>; rel=preload; as=script; nopush","Link: </page-data/app-data.json>; rel=preload; as=fetch; crossorigin; nopush","Link: </page-data/week/rsvp/page-data.json>; rel=preload; as=fetch; crossorigin; nopush"]}